mcp_file_reader/__init__.py
mcp_file_reader-0.2.2.dist-info/licenses/LICENSE.txt
mcp_file_reader-0.2.2.dist-info/METADATA
mcp_file_reader-0.2.2.dist-info/WHEEL
mcp_file_reader-0.2.2.dist-info/entry_points.txt
mcp_file_reader-0.2.2.dist-info/top_level.txt
mcp_file_reader-0.2.2.dist-info/RECORD
