Metadata-Version: 2.4
Name: mcp-file-reader
Version: 0.2.2
Summary: A Model Context Protocol (MCP) service that extracts text content from files using Apache Tika
Author: Nicko van Someren
License-Expression: MIT
Project-URL: Homepage, https://github.com/nickovs/mcp_file_reader
Project-URL: Repository, https://github.com/nickovs/mcp_file_reader
Project-URL: Issues, https://github.com/nickovs/mcp_file_reader/issues
Classifier: Development Status :: 4 - Beta
Classifier: Intended Audience :: Developers
Classifier: Programming Language :: Python :: 3
Classifier: Programming Language :: Python :: 3.8
Classifier: Programming Language :: Python :: 3.9
Classifier: Programming Language :: Python :: 3.10
Classifier: Programming Language :: Python :: 3.11
Classifier: Programming Language :: Python :: 3.12
Requires-Python: >=3.8
License-File: LICENSE.txt
Requires-Dist: mcp>=1.0.0
Requires-Dist: httpx>=0.25.0
Requires-Dist: docker
Requires-Dist: click
Provides-Extra: dev
Requires-Dist: pytest>=7.0.0; extra == "dev"
Requires-Dist: pytest-asyncio>=0.21.0; extra == "dev"
Requires-Dist: requests>=2.28.0; extra == "dev"
Dynamic: license-file
